fastreg/__init__.py
fastreg/formula.py
fastreg/general.py
fastreg/linear.py
fastreg/meta.py
fastreg/summary.py
fastreg/testing.py
fastreg/tools.py
fastreg/trees.py
fastreg/tests/conftest.py
fastreg/tests/test_formula.py
fastreg/tests/test_general.py
fastreg/tests/test_linear.py
fastreg-1.2.dist-info/LICENSE
fastreg-1.2.dist-info/METADATA
fastreg-1.2.dist-info/WHEEL
fastreg-1.2.dist-info/top_level.txt
fastreg-1.2.dist-info/RECORD
