Metadata-Version: 2.1
Name: fastreg
Version: 1.2
Summary: Fast sparse regressions
Author-email: Doug Hanley <thesecretaryofwar@gmail.com>
License: MIT
Project-URL: Homepage, http://github.com/iamlemec/fastreg
Keywords: statistics,regression,ols,glm
Classifier: License :: OSI Approved :: MIT License
Classifier: Programming Language :: Python
Classifier: Programming Language :: Python :: 3
Requires-Python: >=3.7
License-File: LICENSE
Requires-Dist: numpy
Requires-Dist: scipy
Requires-Dist: pandas
Provides-Extra: glm
Requires-Dist: jax ; extra == 'glm'
Requires-Dist: jaxlib ; extra == 'glm'
Requires-Dist: optax ; extra == 'glm'
